lsoph/__init__.py
lsoph/cli.py
lsoph/log.py
lsoph/backend/__init__.py
lsoph/backend/base.py
lsoph/backend/lsof/__init__.py
lsoph/backend/lsof/backend.py
lsoph/backend/lsof/helpers.py
lsoph/backend/lsof/parse.py
lsoph/backend/psutil/__init__.py
lsoph/backend/psutil/backend.py
lsoph/backend/psutil/helpers.py
lsoph/backend/strace/__init__.py
lsoph/backend/strace/backend.py
lsoph/backend/strace/handlers.py
lsoph/backend/strace/helpers.py
lsoph/backend/strace/parse.py
lsoph/backend/strace/terminate.py
lsoph/monitor/__init__.py
lsoph/monitor/_fileinfo.py
lsoph/monitor/_monitor.py
lsoph/ui/__init__.py
lsoph/ui/app.py
lsoph/ui/detail_screen.py
lsoph/ui/emoji.py
lsoph/ui/file_data_table.py
lsoph/ui/log_screen.py
lsoph/ui/style.css
lsoph/util/__init__.py
lsoph/util/pid.py
lsoph/util/short_path.py
lsoph/util/versioned.py
lsoph-0.0.4.dist-info/entry_points.txt
lsoph-0.0.4.dist-info/licenses/LICENSE.md
lsoph-0.0.4.dist-info/WHEEL
lsoph-0.0.4.dist-info/METADATA
lsoph-0.0.4.dist-info/RECORD
